{"nodes": [{"id": "kit_service", "label": "kit_service.py", "file_type": "code", "source_file": "C:\\Tools\\radan_kitter\\kit_service.py", "source_location": "L1"}, {"id": "kit_service_apply_balance_and_update_kit_texts", "label": "apply_balance_and_update_kit_texts()", "file_type": "code", "source_file": "C:\\Tools\\radan_kitter\\kit_service.py", "source_location": "L21"}, {"id": "kit_service_prepare_kits", "label": "prepare_kits()", "file_type": "code", "source_file": "C:\\Tools\\radan_kitter\\kit_service.py", "source_location": "L49"}, {"id": "kit_service_write_rpd_with_backup", "label": "write_rpd_with_backup()", "file_type": "code", "source_file": "C:\\Tools\\radan_kitter\\kit_service.py", "source_location": "L133"}], "edges": [{"source": "kit_service", "target": "os", "relation": "imports", "confidence": "EXTRACTED", "source_file": "C:\\Tools\\radan_kitter\\kit_service.py", "source_location": "L3", "weight": 1.0}, {"source": "kit_service", "target": "typing", "relation": "imports_from", "confidence": "EXTRACTED", "source_file": "C:\\Tools\\radan_kitter\\kit_service.py", "source_location": "L4", "weight": 1.0}, {"source": "kit_service", "target": "rpd_io", "relation": "imports", "confidence": "EXTRACTED", "source_file": "C:\\Tools\\radan_kitter\\kit_service.py", "source_location": "L6", "weight": 1.0}, {"source": "kit_service", "target": "sym_io", "relation": "imports", "confidence": "EXTRACTED", "source_file": "C:\\Tools\\radan_kitter\\kit_service.py", "source_location": "L7", "weight": 1.0}, {"source": "kit_service", "target": "app_utils", "relation": "imports_from", "confidence": "EXTRACTED", "source_file": "C:\\Tools\\radan_kitter\\kit_service.py", "source_location": "L8", "weight": 1.0}, {"source": "kit_service", "target": "rpd_io", "relation": "imports_from", "confidence": "EXTRACTED", "source_file": "C:\\Tools\\radan_kitter\\kit_service.py", "source_location": "L18", "weight": 1.0}, {"source": "kit_service", "target": "kit_service_apply_balance_and_update_kit_texts", "relation": "contains", "confidence": "EXTRACTED", "source_file": "C:\\Tools\\radan_kitter\\kit_service.py", "source_location": "L21", "weight": 1.0}, {"source": "kit_service", "target": "kit_service_prepare_kits", "relation": "contains", "confidence": "EXTRACTED", "source_file": "C:\\Tools\\radan_kitter\\kit_service.py", "source_location": "L49", "weight": 1.0}, {"source": "kit_service", "target": "kit_service_write_rpd_with_backup", "relation": "contains", "confidence": "EXTRACTED", "source_file": "C:\\Tools\\radan_kitter\\kit_service.py", "source_location": "L133", "weight": 1.0}, {"source": "kit_service_prepare_kits", "target": "kit_service_apply_balance_and_update_kit_texts", "relation": "calls", "confidence": "INFERRED", "source_file": "C:\\Tools\\radan_kitter\\kit_service.py", "source_location": "L67", "weight": 0.8}]}